caped_ai_visualizations/__init__.py
caped_ai_visualizations/_version.py
caped_ai_visualizations/visualize_action_volume_boxes.py
caped_ai_visualizations/visualize_activations.py
caped_ai_visualizations-1.2.7.dist-info/METADATA
caped_ai_visualizations-1.2.7.dist-info/WHEEL
caped_ai_visualizations-1.2.7.dist-info/top_level.txt
caped_ai_visualizations-1.2.7.dist-info/RECORD
