Metadata-Version: 2.1
Name: caped-ai-visualizations
Version: 1.2.7
Summary: Visualization toolkit for oneat bounding boxes, activation functions, vollseg visualization
Home-page: https://github.com/Kapoorlabs-CAPED/caped-ai-visualizations/
Author: Varun Kapoor
Author-email: randomaccessiblekapoor@gmail.com
Classifier: Development Status :: 3 - Alpha
Classifier: Natural Language :: English
Classifier: License :: OSI Approved :: MIT License
Classifier: Operating System :: OS Independent
Classifier: Programming Language :: Python
Classifier: Programming Language :: Python :: 3.9
Requires-Dist: oneat
